[{
    "id": 1,
    "image": "/Clicky-Game/assets/images/poop.jpeg",
    "clicked": false
  },
  {
    "id": 2,
    "image": "/Clicky-Game/assets/images/happy.jpeg",
    "clicked": false
  },
  {
    "id": 3,
    "image": "/Clicky-Game/assets/images/hearth-eyes.jpeg",
    "clicked": false
  },
  {
    "id": 4,
    "image": "/Clicky-Game/assets/images/thumbs-up.jpeg",
    "clicked": false
  },
  {
    "id": 5,
    "image": "/Clicky-Game/assets/images/happy.jpeg",
    "clicked": false
  },
  {
    "id": 6,
    "image": "/Clicky-Game/assets/images/hearth-eyes.jpeg",
    "clicked": false
  },
  {
    "id": 7,
    "image": "/Clicky-Game/assets/images/kiss.jpeg",
    "clicked": false
  },
  {
    "id": 8,
    "image": "/Clicky-Game/assets/images/sad.jpeg",
    "clicked": false
  },
  {
    "id": 9,
    "image": "/Clicky-Game/assets/images/silly.jpeg",
    "clicked": false
  },
  {
    "id": 10,
    "image": "/Clicky-Game/assets/images/lol.jpeg",
    "clicked": false
  },
  {
    "id": 11,
    "image": "/Clicky-Game/assets/images/blowing kiss.jpeg",
    "clicked": false
  },
  {
    "id": 12,
    "image": "/Clicky-Game/assets/images/***.jpeg",
    "clicked": false
  }
]